packaging_demo/__init__.py
packaging_demo/app.py
packaging_demo_nagan-0.0.4.dist-info/METADATA
packaging_demo_nagan-0.0.4.dist-info/WHEEL
packaging_demo_nagan-0.0.4.dist-info/top_level.txt
packaging_demo_nagan-0.0.4.dist-info/RECORD
